readpw.py
readpw-1.0.0.dist-info/DESCRIPTION.rst
readpw-1.0.0.dist-info/METADATA
readpw-1.0.0.dist-info/RECORD
readpw-1.0.0.dist-info/WHEEL
readpw-1.0.0.dist-info/metadata.json
readpw-1.0.0.dist-info/top_level.txt
readpw-1.0.0.dist-info/zip-safe
