Metadata-Version: 2.0
Name: readpw
Version: 1.0.0
Summary: A project to read password leak files easily. More documentation in github page.
Home-page: https://github.com/rchatterjee/Passwords
Author: rahul
Author-email: rahul@cs.cornell.edu
License: MIT
Platform: UNKNOWN
Classifier: Development Status :: 4 - Beta
Classifier: Topic :: Utilities
Classifier: License :: OSI Approved :: MIT License
Requires-Dist: numpy
Requires-Dist: marisa-trie
